nti/__init__.py
nti/intid/__init__.py
nti/intid/common.py
nti/intid/configure.zcml
nti/intid/containers.py
nti/intid/interfaces.py
nti/intid/subscribers.py
nti/intid/utility.py
nti/intid/wref.py
nti/intid/tests/__init__.py
nti/intid/tests/test_common.py
nti/intid/tests/test_intid_wref.py
nti/intid/tests/test_modules.py
nti/intid/tests/test_utility.py
nti_intid-1.1.0.dist-info/licenses/LICENSE
nti_intid-1.1.0.dist-info/METADATA
nti_intid-1.1.0.dist-info/WHEEL
nti_intid-1.1.0.dist-info/top_level.txt
nti_intid-1.1.0.dist-info/zip-safe
nti_intid-1.1.0.dist-info/RECORD
